{"cameraMode":{"drawMode":0,"name":"Shaded","section":"Shading Mode"},"sceneLighting":true,"audioPlay":false,"sceneViewState":{"showFog":true,"showMaterialUpdate":false,"showSkybox":true,"showFlares":true,"showImageEffects":true,"showParticleSystems":true},"in2DMode":false,"pivot":{"x":-0.1558375060558319,"y":0.3612769842147827,"z":-1.5064667463302613},"rotation":{"x":0.3258674740791321,"y":-0.04960382357239723,"z":0.0171195100992918,"w":0.9439755082130432},"size":1.4025144577026368,"orthographic":false}